mpl_composite/__init__.py
mpl_composite/dummy.py
mpl_composite-0.0.2.dist-info/METADATA
mpl_composite-0.0.2.dist-info/WHEEL
mpl_composite-0.0.2.dist-info/licenses/LICENSE
mpl_composite-0.0.2.dist-info/RECORD
