Metadata-Version: 2.4
Name: mpl-composite
Version: 0.0.2
Summary: Matplotlib wrapper for composite figure building.
Project-URL: Source, https://github.com/bertpl/mpl-composite
Project-URL: ChangeLog, https://github.com/bertpl/mpl-composite/blob/develop/CHANGELOG.md
Project-URL: Issues, https://github.com/bertpl/mpl-composite/issues
Project-URL: Roadmap, https://github.com/bertpl/mpl-composite/milestones
Author-email: Bert Pluymers <bert.pluymers@gmail.com>
License-File: LICENSE
Requires-Python: >=3.11
Requires-Dist: matplotlib>=3.8
Requires-Dist: numpy>=2.0.0
